{".class": "MypyFile", "_fullname": "server.credentials", "is_partial_stub_package": false, "is_stub": false, "names": {".class": "SymbolTable", "DB_HOST": {".class": "SymbolTableNode", "kind": "Gdef", "node": {".class": "Var", "flags": ["is_ready"], "fullname": "server.credentials.DB_HOST", "name": "DB_HOST", "type": "builtins.str"}}, "DB_NAME": {".class": "SymbolTableNode", "kind": "Gdef", "node": {".class": "Var", "flags": ["is_ready"], "fullname": "server.credentials.DB_NAME", "name": "DB_NAME", "type": "builtins.str"}}, "DB_PASSWORD": {".class": "SymbolTableNode", "kind": "Gdef", "node": {".class": "Var", "flags": ["is_ready"], "fullname": "server.credentials.DB_PASSWORD", "name": "DB_PASSWORD", "type": "builtins.str"}}, "DB_PORT": {".class": "SymbolTableNode", "kind": "Gdef", "node": {".class": "Var", "flags": ["is_ready"], "fullname": "server.credentials.DB_PORT", "name": "DB_PORT", "type": "builtins.int"}}, "DB_USER": {".class": "SymbolTableNode", "kind": "Gdef", "node": {".class": "Var", "flags": ["is_ready"], "fullname": "server.credentials.DB_USER", "name": "DB_USER", "type": "builtins.str"}}, "__doc__": {".class": "SymbolTableNode", "kind": "Gdef", "node": {".class": "Var", "flags": ["is_ready"], "fullname": "server.credentials.__doc__", "name": "__doc__", "type": "builtins.str"}}, "__file__": {".class": "SymbolTableNode", "kind": "Gdef", "node": {".class": "Var", "flags": ["is_ready"], "fullname": "server.credentials.__file__", "name": "__file__", "type": "builtins.str"}}, "__name__": {".class": "SymbolTableNode", "kind": "Gdef", "node": {".class": "Var", "flags": ["is_ready"], "fullname": "server.credentials.__name__", "name": "__name__", "type": "builtins.str"}}, "__package__": {".class": "SymbolTableNode", "kind": "Gdef", "node": {".class": "Var", "flags": ["is_ready"], "fullname": "server.credentials.__package__", "name": "__package__", "type": "builtins.str"}}}, "path": "/home/nulven/abelian/landscaping/server/credentials.py"}