{".class": "MypyFile", "_fullname": "server.routes", "is_partial_stub_package": false, "is_stub": false, "names": {".class": "SymbolTable", "Blueprint": {".class": "SymbolTableNode", "cross_ref": "flask.blueprints.Blueprint", "kind": "Gdef"}, "Flask": {".class": "SymbolTableNode", "cross_ref": "flask.app.Flask", "kind": "Gdef"}, "ShopifyPermissions": {".class": "SymbolTableNode", "cross_ref": "server.enums.ShopifyPermissions", "kind": "Gdef"}, "__doc__": {".class": "SymbolTableNode", "kind": "Gdef", "node": {".class": "Var", "flags": ["is_ready"], "fullname": "server.routes.__doc__", "name": "__doc__", "type": "builtins.str"}}, "__file__": {".class": "SymbolTableNode", "kind": "Gdef", "node": {".class": "Var", "flags": ["is_ready"], "fullname": "server.routes.__file__", "name": "__file__", "type": "builtins.str"}}, "__name__": {".class": "SymbolTableNode", "kind": "Gdef", "node": {".class": "Var", "flags": ["is_ready"], "fullname": "server.routes.__name__", "name": "__name__", "type": "builtins.str"}}, "__package__": {".class": "SymbolTableNode", "kind": "Gdef", "node": {".class": "Var", "flags": ["is_ready"], "fullname": "server.routes.__package__", "name": "__package__", "type": "builtins.str"}}, "api": {".class": "SymbolTableNode", "kind": "Gdef", "node": {".class": "Var", "flags": ["is_suppressed_import", "is_ready"], "fullname": "server.routes.api", "name": "api", "type": {".class": "AnyType", "missing_import_name": "server.routes.api", "source_any": null, "type_of_any": 3}}}, "app_bp": {".class": "SymbolTableNode", "kind": "Gdef", "node": {".class": "Var", "flags": [], "fullname": "server.routes.app_bp", "name": "app_bp", "type": {".class": "AnyType", "missing_import_name": null, "source_any": null, "type_of_any": 1}}}, "db": {".class": "SymbolTableNode", "cross_ref": "server.models.db", "kind": "Gdef"}, "empty": {".class": "SymbolTableNode", "cross_ref": "server.routes.helpers.empty", "kind": "Gdef"}, "generate_token": {".class": "SymbolTableNode", "kind": "Gdef", "node": {".class": "Decorator", "func": {".class": "FuncDef", "arg_kinds": [], "arg_names": [], "flags": ["is_decorated"], "fullname": "server.routes.generate_token", "name": "generate_token", "type": null}, "is_overload": false, "var": {".class": "Var", "flags": ["is_ready"], "fullname": null, "name": "generate_token", "type": {".class": "AnyType", "missing_import_name": null, "source_any": {".class": "AnyType", "missing_import_name": null, "source_any": null, "type_of_any": 1}, "type_of_any": 7}}}}, "get_access_token": {".class": "SymbolTableNode", "cross_ref": "server.shopify_api.authentication.get_access_token", "kind": "Gdef"}, "index": {".class": "SymbolTableNode", "kind": "Gdef", "node": {".class": "Decorator", "func": {".class": "FuncDef", "arg_kinds": [], "arg_names": [], "flags": ["is_decorated"], "fullname": "server.routes.index", "name": "index", "type": null}, "is_overload": false, "var": {".class": "Var", "flags": ["is_ready"], "fullname": null, "name": "index", "type": {".class": "AnyType", "missing_import_name": null, "source_any": {".class": "AnyType", "missing_import_name": null, "source_any": null, "type_of_any": 1}, "type_of_any": 7}}}}, "install": {".class": "SymbolTableNode", "kind": "Gdef", "node": {".class": "Decorator", "func": {".class": "FuncDef", "arg_kinds": [], "arg_names": [], "flags": ["is_decorated"], "fullname": "server.routes.install", "name": "install", "type": null}, "is_overload": false, "var": {".class": "Var", "flags": ["is_ready"], "fullname": null, "name": "install", "type": {".class": "AnyType", "missing_import_name": null, "source_any": {".class": "AnyType", "missing_import_name": null, "source_any": null, "type_of_any": 1}, "type_of_any": 7}}}}, "jsonify": {".class": "SymbolTableNode", "cross_ref": "flask.json.jsonify", "kind": "Gdef"}, "lander": {".class": "SymbolTableNode", "kind": "Gdef", "node": {".class": "Decorator", "func": {".class": "FuncDef", "arg_kinds": [], "arg_names": [], "flags": ["is_decorated"], "fullname": "server.routes.lander", "name": "lander", "type": null}, "is_overload": false, "var": {".class": "Var", "flags": ["is_ready"], "fullname": null, "name": "lander", "type": {".class": "AnyType", "missing_import_name": null, "source_any": {".class": "AnyType", "missing_import_name": null, "source_any": null, "type_of_any": 1}, "type_of_any": 7}}}}, "login": {".class": "SymbolTableNode", "kind": "Gdef", "node": {".class": "Decorator", "func": {".class": "FuncDef", "arg_kinds": [], "arg_names": [], "flags": ["is_decorated"], "fullname": "server.routes.login", "name": "login", "type": null}, "is_overload": false, "var": {".class": "Var", "flags": ["is_ready"], "fullname": null, "name": "login", "type": {".class": "AnyType", "missing_import_name": null, "source_any": {".class": "AnyType", "missing_import_name": null, "source_any": null, "type_of_any": 1}, "type_of_any": 7}}}}, "logout": {".class": "SymbolTableNode", "kind": "Gdef", "node": {".class": "Decorator", "func": {".class": "FuncDef", "arg_kinds": [], "arg_names": [], "flags": ["is_decorated"], "fullname": "server.routes.logout", "name": "logout", "type": null}, "is_overload": false, "var": {".class": "Var", "flags": ["is_ready"], "fullname": null, "name": "logout", "type": {".class": "AnyType", "missing_import_name": null, "source_any": {".class": "AnyType", "missing_import_name": null, "source_any": null, "type_of_any": 1}, "type_of_any": 7}}}}, "make_response": {".class": "SymbolTableNode", "cross_ref": "flask.helpers.make_response", "kind": "Gdef"}, "nested_blueprint": {".class": "SymbolTableNode", "cross_ref": "server.routes.nested_blueprint.nested_blueprint", "kind": "Gdef"}, "register": {".class": "SymbolTableNode", "kind": "Gdef", "node": {".class": "Decorator", "func": {".class": "FuncDef", "arg_kinds": [], "arg_names": [], "flags": ["is_decorated"], "fullname": "server.routes.register", "name": "register", "type": null}, "is_overload": false, "var": {".class": "Var", "flags": ["is_ready"], "fullname": null, "name": "register", "type": {".class": "AnyType", "missing_import_name": null, "source_any": {".class": "AnyType", "missing_import_name": null, "source_any": null, "type_of_any": 1}, "type_of_any": 7}}}}, "render_template": {".class": "SymbolTableNode", "cross_ref": "flask.templating.render_template", "kind": "Gdef"}, "request": {".class": "SymbolTableNode", "cross_ref": "flask.globals.request", "kind": "Gdef"}, "valid_email": {".class": "SymbolTableNode", "cross_ref": "server.routes.helpers.valid_email", "kind": "Gdef"}}, "path": "/home/nulven/abelian/shopify/server/routes/__init__.py"}